Py2Crawl/__init__.py
Py2Crawl/exceptions.py
Py2Crawl/py2crawl.py
Py2Crawl/spider.py
Py2Crawl/http/__init__.py
Py2Crawl/http/a_http.py
Py2Crawl/http/methods.py
Py2Crawl/http/pwb_http.py
Py2Crawl/middleware/__init__.py
Py2Crawl/middleware/cookie_middleware.py
Py2Crawl/middleware/req_res_middleware.py
Py2Crawl/parser/__init__.py
Py2Crawl/parser/parser.py
Py2Crawl/settings/__init__.py
Py2Crawl/settings/base_settings.py
Py2Crawl/settings/parser_settings.py
Py2Crawl/settings/spider_settings.py
Py2Crawl/utils/__init__.py
Py2Crawl/utils/input_validation.py
Py2Crawl/utils/logger.py
Py2Crawl/utils/request.py
Py2Crawl/utils/response.py
tests/__init__.py
Py2Crawl-1.0.7.dist-info/LICENSE
Py2Crawl-1.0.7.dist-info/METADATA
Py2Crawl-1.0.7.dist-info/WHEEL
Py2Crawl-1.0.7.dist-info/top_level.txt
Py2Crawl-1.0.7.dist-info/RECORD
